LICENSE
MANIFEST.in
README.rst
setup.py
itunes_iap2.egg-info/PKG-INFO
itunes_iap2.egg-info/SOURCES.txt
itunes_iap2.egg-info/dependency_links.txt
itunes_iap2.egg-info/requires.txt
itunes_iap2.egg-info/top_level.txt
itunesiap/__init__.py
itunesiap/core.py
itunesiap/exceptions.py
itunesiap/shortcut.py
itunesiap/version.txt