Metadata-Version: 1.1
Name: itunes-iap2
Version: 0.6.2.2
Summary: Apple iTunes In-app purchase verification api.
Home-page: https://github.com/nana-music/itunes-iap
Author: kiri1120
Author-email: kazuki.s1120@gmail.com
License: UNKNOWN
Platform: UNKNOWN
Classifier: Intended Audience :: Developers
Classifier: Operating System :: OS Independent
Classifier: Programming Language :: Python
Classifier: Programming Language :: Python :: 2
Classifier: Programming Language :: Python :: 2.6
Classifier: Programming Language :: Python :: 2.7
Classifier: Programming Language :: Python :: 3
Classifier: Programming Language :: Python :: 3.2
Classifier: Programming Language :: Python :: 3.3
